sccircuitbuilder/.DS_Store
sccircuitbuilder/__init__.py
sccircuitbuilder/branch_element.py
sccircuitbuilder/canvas.py
sccircuitbuilder/canvas_element.py
sccircuitbuilder/caretaker.py
sccircuitbuilder/circuit.py
sccircuitbuilder/circuitbuilder.py
sccircuitbuilder/connection.py
sccircuitbuilder/constants.py
sccircuitbuilder/node.py
sccircuitbuilder/circuits/.DS_Store
sccircuitbuilder/circuits/Cos2PhiQubit.circuit
sccircuitbuilder/circuits/FluxQubit.circuit
sccircuitbuilder/circuits/Fluxonium.circuit
sccircuitbuilder/circuits/Transmon.circuit
sccircuitbuilder/circuits/TunableTransmon.circuit
sccircuitbuilder/circuits/ZeroPi.circuit
sccircuitbuilder/elements/Inductor.svg
sccircuitbuilder/elements/JJ.svg
sccircuitbuilder/elements/capacitor.svg
sccircuitbuilder/elements/ground.svg
sccircuitbuilder/icons/.DS_Store
sccircuitbuilder/icons/clear.png
sccircuitbuilder/icons/redo.png
sccircuitbuilder/icons/rotate.png
sccircuitbuilder/icons/split.png
sccircuitbuilder/icons/trash.png
sccircuitbuilder/icons/undo.png
sccircuitbuilder-0.0.3.dist-info/METADATA
sccircuitbuilder-0.0.3.dist-info/WHEEL
sccircuitbuilder-0.0.3.dist-info/licenses/LICENSE
sccircuitbuilder-0.0.3.dist-info/RECORD
