Metadata-Version: 2.1
Name: sccircuitbuilder
Version: 0.0.3
Summary: A graphical user interface to create superconducting circuits intended to accompany scQubits
Project-URL: Homepage, https://github.com/benmcdonough20/SuperconductingCircuitBuilder
Project-URL: Tracker, https://github.com/benmcdonough20/SuperconductingCircuitBuilder/issues
Author-email: Ben McDonough <ben.mcdonough@yale.edu>
License-File: LICENSE
Keywords: cQED,circuit QED,quantum,quantum computing,superconducting circuits
Classifier: License :: OSI Approved :: MIT License
Classifier: Operating System :: OS Independent
Classifier: Programming Language :: Python :: 3
Requires-Python: >=3.7
Requires-Dist: numpy
Requires-Dist: pyside6
